nonebot_plugin_animepush/__init__.py
nonebot_plugin_animepush/config.py
nonebot_plugin_animepush/model.py
nonebot_plugin_animepush/utils.py
nonebot_plugin_animepush/templates/anime_schedule.html
nonebot_plugin_animepush/templates/footer.html
nonebot_plugin_animepush/templates/header.html
nonebot_plugin_animepush-0.0.3.dist-info/LICENSE
nonebot_plugin_animepush-0.0.3.dist-info/METADATA
nonebot_plugin_animepush-0.0.3.dist-info/WHEEL
nonebot_plugin_animepush-0.0.3.dist-info/top_level.txt
nonebot_plugin_animepush-0.0.3.dist-info/RECORD
