Metadata-Version: 2.1
Name: nonebot-plugin-animepush
Version: 0.0.3
Summary: 将每日更新番剧渲染为图片
Home-page: https://github.com/huanxin996/nonebot-plugin-animepush
Author: huanxin996
Author-email: mc.xiaolang@foxmail.com
Classifier: Programming Language :: Python :: 3
Classifier: License :: OSI Approved :: MIT License
Classifier: Operating System :: OS Independent
License-File: LICENSE
Requires-Dist: nonebot-plugin-apscheduler<=0.5.0
Requires-Dist: nonebot-plugin-tortoise-orm<=0.1.4
Requires-Dist: nonebot-plugin-htmlrender<=0.6.2
Requires-Dist: nonebot-plugin-localstore<=0.7.3
